firethon/__init__.py
firethon/config.py
firethon/firebase.py
firethon-0.1.0.dist-info/METADATA
firethon-0.1.0.dist-info/WHEEL
firethon-0.1.0.dist-info/top_level.txt
firethon-0.1.0.dist-info/RECORD
