Metadata-Version: 2.1
Name: firethon
Version: 0.1.0
Summary: A simple API wrapper for firebase
Home-page: https://github.com/dalerzafarovich/firethon
Author: Daler Sattarov
Author-email: zdaler014@gmail.com
License: MIT
Platform: UNKNOWN
Classifier: License :: OSI Approved :: MIT License
Classifier: Programming Language :: Python :: 3
Classifier: Programming Language :: Python :: 3.7
Requires-Dist: requests
Requires-Dist: google-auth
